tadatakit/__init__.py
tadatakit/class_generator/__init__.py
tadatakit/class_generator/base_classes.py
tadatakit/class_generator/definition_registry.py
tadatakit/class_generator/polymorph_factory.py
tadatakit/class_generator/schema_loader.py
tadatakit/class_generator/utils.py
tadatakit/classes/__init__.py
tadatakit-0.1.1.dist-info/LICENSE
tadatakit-0.1.1.dist-info/METADATA
tadatakit-0.1.1.dist-info/WHEEL
tadatakit-0.1.1.dist-info/RECORD
