Metadata-Version: 2.1
Name: tadatakit
Version: 0.1.1
Summary: A Python library for parsing and handling data exported by TA Instruments' TRIOS JSON Export
Home-page: https://www.tainstruments.com/
License: MIT
Keywords: TA Instruments,TRIOS,JSON,data parsing,data analysis,materials science,DSC,TGA,rheology
Author: Stuart Cook
Author-email: stuart_cook@waters.com
Requires-Python: >=3.9,<4.0
Classifier: Development Status :: 4 - Beta
Classifier: Intended Audience :: Science/Research
Classifier: License :: OSI Approved :: MIT License
Classifier: Programming Language :: Python :: 3
Classifier: Programming Language :: Python :: 3.9
Classifier: Programming Language :: Python :: 3.10
Classifier: Programming Language :: Python :: 3.11
Classifier: Programming Language :: Python :: 3.12
Classifier: Topic :: Scientific/Engineering :: Chemistry
Classifier: Topic :: Scientific/Engineering :: Physics
Classifier: Topic :: Software Development :: Libraries :: Python Modules
Requires-Dist: pandas (>=2.1.4,<3.0.0)
Requires-Dist: tainstruments-triosdataschema (==0.1.17)
Project-URL: Repository, https://github.com/TA-Instruments/tadatakit
